llm_flow_engine/__init__.py
llm_flow_engine/builtin_functions.py
llm_flow_engine/dsl_loader.py
llm_flow_engine/executor.py
llm_flow_engine/executor_result.py
llm_flow_engine/flow_engine.py
llm_flow_engine/model_config.py
llm_flow_engine/utils.py
llm_flow_engine/workflow.py
llm_flow_engine/functions/__init__.py
llm_flow_engine/functions/agent.py
llm_flow_engine/functions/analysis_llm.py
llm_flow_engine/functions/control_network.py
llm_flow_engine/functions/core.py
llm_flow_engine/functions/data_flow.py
llm_flow_engine/functions/file_time.py
llm_flow_engine/functions/knowledge_base.py
llm_flow_engine/functions/llm_api.py
llm_flow_engine/functions/rag.py
llm_flow_engine/functions/text_data.py
llm_flow_engine/functions/tools.py
llm_flow_engine-0.7.4.dist-info/licenses/LICENSE
llm_flow_engine-0.7.4.dist-info/METADATA
llm_flow_engine-0.7.4.dist-info/WHEEL
llm_flow_engine-0.7.4.dist-info/top_level.txt
llm_flow_engine-0.7.4.dist-info/RECORD
